MANIFEST.in
README.md
setup.cfg
setup.py
adaptisc/__init__.py
adaptisc/adapt.py
adaptisc/bitparse.py
adaptisc/jedparse.py
adaptisc/jtagUnsupportedDevice.py
adaptisc/utils.py
adaptisc.egg-info/PKG-INFO
adaptisc.egg-info/SOURCES.txt
adaptisc.egg-info/dependency_links.txt
adaptisc.egg-info/entry_points.txt
adaptisc.egg-info/requires.txt
adaptisc.egg-info/top_level.txt
adaptisc/deviceDrivers/__init__.py
adaptisc/deviceDrivers/xilinxPlatformFlash.py
adaptisc/deviceDrivers/xilinxSpartan.py
adaptisc/deviceDrivers/xilinxCPLD/__init__.py
adaptisc/deviceDrivers/xilinxCPLD/map.py