Metadata-Version: 1.0
Name: adaptisc
Version: 0.2.0
Summary: Reference implementation of a tool using the proteusisc library for configuring ISC devices.
Home-page: https://github.com/diamondman/Adapt
Author: Jessy Diamond Exum
Author-email: jessy.diamondman@gmail.com
License: LGPL 2.1
Platform: any
